contextgem/__init__.py
contextgem/internal/__init__.py
contextgem/internal/data_models.py
contextgem/internal/decorators.py
contextgem/internal/exceptions.py
contextgem/internal/items.py
contextgem/internal/loggers.py
contextgem/internal/registry.py
contextgem/internal/suppressions.py
contextgem/internal/utils.py
contextgem/internal/base/__init__.py
contextgem/internal/base/abstract.py
contextgem/internal/base/aspects.py
contextgem/internal/base/attrs.py
contextgem/internal/base/concepts.py
contextgem/internal/base/data_models.py
contextgem/internal/base/documents.py
contextgem/internal/base/examples.py
contextgem/internal/base/images.py
contextgem/internal/base/instances.py
contextgem/internal/base/items.py
contextgem/internal/base/llms.py
contextgem/internal/base/md_text.py
contextgem/internal/base/mixins.py
contextgem/internal/base/paras_and_sents.py
contextgem/internal/base/pipelines.py
contextgem/internal/base/serialization.py
contextgem/internal/base/utils.py
contextgem/internal/converters/__init__.py
contextgem/internal/converters/docx/__init__.py
contextgem/internal/converters/docx/base.py
contextgem/internal/converters/docx/namespaces.py
contextgem/internal/converters/docx/package.py
contextgem/internal/converters/docx/utils.py
contextgem/internal/llm_output_structs/__init__.py
contextgem/internal/llm_output_structs/aspect_structs.py
contextgem/internal/llm_output_structs/concept_structs.py
contextgem/internal/llm_output_structs/utils.py
contextgem/internal/prompts/extract_aspect_items.j2
contextgem/internal/prompts/extract_concept_items.j2
contextgem/internal/system/default_system_message.j2
contextgem/internal/typings/__init__.py
contextgem/internal/typings/strings_to_types.py
contextgem/internal/typings/typed_class_utils.py
contextgem/internal/typings/types.py
contextgem/internal/typings/types_normalization.py
contextgem/internal/typings/types_to_strings.py
contextgem/internal/typings/user_type_hints_validation.py
contextgem-0.19.4.dist-info/METADATA
contextgem-0.19.4.dist-info/WHEEL
contextgem-0.19.4.dist-info/licenses/LICENSE
contextgem-0.19.4.dist-info/licenses/NOTICE
contextgem-0.19.4.dist-info/RECORD
