Metadata-Version: 2.4
Name: contextgem
Version: 0.19.4
Summary: Effortless LLM extraction from documents
Project-URL: Homepage, https://github.com/shcherbak-ai/contextgem
Project-URL: Documentation, https://github.com/shcherbak-ai/contextgem/blob/main/README.md
Project-URL: Repository, https://github.com/shcherbak-ai/contextgem.git
Project-URL: Bug Tracker, https://github.com/shcherbak-ai/contextgem/issues
Author-email: shcherbak-ai <sergii@shcherbak.ai>
Maintainer-email: shcherbak-ai <sergii@shcherbak.ai>
License: Apache-2.0
License-File: LICENSE
License-File: NOTICE
Keywords: artificial-intelligence,aspect-extraction,automated-prompting,concept-extraction,content-extraction,context-aware,contextgem,contract-analysis,contract-automation,contract-intelligence,contract-management,contract-parsing,contract-review,data-extraction,document,document-analysis,document-extraction,document-intelligence,document-parsing,document-pipeline,document-processing,document-qa,document-understanding,docx,entity-extraction,extraction-justifications,extraction-pipeline,fintech,
Classifier: Development Status :: 4 - Beta
Classifier: Intended Audience :: Developers
Classifier: Intended Audience :: Education
Classifier: Intended Audience :: Financial and Insurance Industry
Classifier: Intended Audience :: Information Technology
Classifier: Intended Audience :: Legal Industry
Classifier: Intended Audience :: Science/Research
Classifier: License :: OSI Approved :: Apache Software License
Classifier: Operating System :: OS Independent
Classifier: Programming Language :: Python :: 3
Classifier: Programming Language :: Python :: 3.10
Classifier: Programming Language :: Python :: 3.11
Classifier: Programming Language :: Python :: 3.12
Classifier: Programming Language :: Python :: 3.13
Classifier: Topic :: Education
Classifier: Topic :: Office/Business
Classifier: Topic :: Scientific/Engineering :: Artificial Intelligence
Classifier: Topic :: Scientific/Engineering :: Image Recognition
Classifier: Topic :: Scientific/Engineering :: Information Analysis
Classifier: Topic :: Software Development :: Libraries :: Application Frameworks
Classifier: Topic :: Software Development :: Libraries :: Python Modules
Classifier: Topic :: Text Processing :: General
Classifier: Topic :: Text Processing :: Linguistic
Requires-Python: <3.14,>=3.10
Requires-Dist: aiolimiter<2.0.0,>=1.2.1
Requires-Dist: colorlog<7.0.0,>=6.9.0
Requires-Dist: fastjsonschema<3.0.0,>=2.21.2
Requires-Dist: genai-prices==0.0.49
Requires-Dist: jinja2<4.0.0,>=3.1.5
Requires-Dist: litellm==1.80.10
Requires-Dist: lxml<6.0.0,>=5.4.0
Requires-Dist: openai==2.13.0
Requires-Dist: pillow<12.0.0,>=11.3.0
Requires-Dist: pydantic<3.0.0,>=2.10.6
Requires-Dist: python-ulid<4.0.0,>=3.0.0
Requires-Dist: tenacity<10.0.0,>=9.1.2
Requires-Dist: typing-extensions<5.0.0,>=4.14.1
Requires-Dist: wtpsplit-lite<0.3.0,>=0.2.0
